mononoqe/data/__init__.py
mononoqe/data/dataset.py
mononoqe/data/training_data.py
mononoqe/data/validation_data.py
mononoqe/inference/__init__.py
mononoqe/inference/runner.py
mononoqe/models/__init__.py
mononoqe/models/model.py
mononoqe/models/layers/__init__.py
mononoqe/models/layers/classical/__init__.py
mononoqe/models/layers/classical/add.py
mononoqe/models/layers/classical/average_pool_2d.py
mononoqe/models/layers/classical/batch_norm_1d.py
mononoqe/models/layers/classical/batch_norm_2d.py
mononoqe/models/layers/classical/concat.py
mononoqe/models/layers/classical/conv_1d.py
mononoqe/models/layers/classical/conv_2d.py
mononoqe/models/layers/classical/deconv_1d.py
mononoqe/models/layers/classical/deconv_2d.py
mononoqe/models/layers/classical/flatten.py
mononoqe/models/layers/classical/fourier_features_1d.py
mononoqe/models/layers/classical/fourier_features_2d.py
mononoqe/models/layers/classical/group_norm.py
mononoqe/models/layers/classical/identity.py
mononoqe/models/layers/classical/instance_norm.py
mononoqe/models/layers/classical/leaky_relu.py
mononoqe/models/layers/classical/linear.py
mononoqe/models/layers/classical/max_pool_2d.py
mononoqe/models/layers/classical/mish.py
mononoqe/models/layers/classical/mul.py
mononoqe/models/layers/classical/pca.py
mononoqe/models/layers/classical/pixelshuffle.py
mononoqe/models/layers/classical/prelu.py
mononoqe/models/layers/classical/relu.py
mononoqe/models/layers/classical/repeat.py
mononoqe/models/layers/classical/resblock.py
mononoqe/models/layers/classical/reshape.py
mononoqe/models/layers/classical/sigmoid.py
mononoqe/models/layers/classical/softmax.py
mononoqe/models/layers/classical/subpixelconv_2d.py
mononoqe/models/layers/classical/sum.py
mononoqe/models/layers/quantum/__init__.py
mononoqe/models/layers/quantum/boson_sampling.py
mononoqe/models/layers/quantum/photonic_circuit.py
mononoqe/models/layers/quantum/qconv_2d.py
mononoqe/models/layers/quantum/slos_circuit.py
mononoqe-0.1.2.dist-info/licenses/LICENSE
mononoqe-0.1.2.dist-info/METADATA
mononoqe-0.1.2.dist-info/WHEEL
mononoqe-0.1.2.dist-info/top_level.txt
mononoqe-0.1.2.dist-info/RECORD
