Metadata-Version: 2.4
Name: mononoqe
Version: 0.1.2
Summary: A simple python library to mix Neural Network and Quantum computing
License: Apache-2.0
Project-URL: Repository, https://github.com/QuantumCommons/mononoqe
Classifier: Programming Language :: Python :: 3
Classifier: Operating System :: OS Independent
Classifier: Intended Audience :: Developers
Classifier: Intended Audience :: Science/Research
Classifier: Topic :: Scientific/Engineering
Requires-Python: >=3.10
License-File: LICENSE
Requires-Dist: fire==0.7.0
Requires-Dist: perceval-quandela==1.1.0
Requires-Dist: lightning==2.5
Requires-Dist: torch==2.9.1
Requires-Dist: torchvision==0.24.1
Requires-Dist: tensorboard==2.18.0
Requires-Dist: dataclasses-json
Requires-Dist: timm
Requires-Dist: pandas
Requires-Dist: numpy==2.3.5
Requires-Dist: scikit-learn==1.8.0
Requires-Dist: seaborn==0.13.2
Dynamic: license-file
